odoo/addons/analytic_tag_dimension_purchase_warning/README.rst
odoo/addons/analytic_tag_dimension_purchase_warning/__init__.py
odoo/addons/analytic_tag_dimension_purchase_warning/__manifest__.py
odoo/addons/analytic_tag_dimension_purchase_warning/i18n/analytic_tag_dimension_purchase_warning.pot
odoo/addons/analytic_tag_dimension_purchase_warning/i18n/ca.po
odoo/addons/analytic_tag_dimension_purchase_warning/i18n/de.po
odoo/addons/analytic_tag_dimension_purchase_warning/i18n/es.po
odoo/addons/analytic_tag_dimension_purchase_warning/i18n/es_CO.po
odoo/addons/analytic_tag_dimension_purchase_warning/i18n/fr.po
odoo/addons/analytic_tag_dimension_purchase_warning/models/__init__.py
odoo/addons/analytic_tag_dimension_purchase_warning/models/purchase.py
odoo/addons/analytic_tag_dimension_purchase_warning/readme/CONFIGURE.rst
odoo/addons/analytic_tag_dimension_purchase_warning/readme/CONTRIBUTORS.rst
odoo/addons/analytic_tag_dimension_purchase_warning/readme/DESCRIPTION.rst
odoo/addons/analytic_tag_dimension_purchase_warning/static/description/icon.png
odoo/addons/analytic_tag_dimension_purchase_warning/static/description/index.html
odoo12_addon_analytic_tag_dimension_purchase_warning-12.0.1.0.0.99.dev6.dist-info/METADATA
odoo12_addon_analytic_tag_dimension_purchase_warning-12.0.1.0.0.99.dev6.dist-info/WHEEL
odoo12_addon_analytic_tag_dimension_purchase_warning-12.0.1.0.0.99.dev6.dist-info/top_level.txt
odoo12_addon_analytic_tag_dimension_purchase_warning-12.0.1.0.0.99.dev6.dist-info/RECORD
